pyngeso/__init__.py
pyngeso/configure_logging.py
pyngeso/exceptions.py
pyngeso/pyngeso.py
pyngeso/resources.py
pyngeso-0.3.7.dist-info/LICENSE.txt
pyngeso-0.3.7.dist-info/METADATA
pyngeso-0.3.7.dist-info/WHEEL
pyngeso-0.3.7.dist-info/RECORD
