Metadata-Version: 2.1
Name: pyngeso
Version: 0.3.7
Summary: Simple python wrapper for the National Grid ESO Portal
Home-page: https://github.com/atsangarides/pyngeso
License: MIT
Keywords: api,energy
Author: atsangarides
Author-email: andreas_tsangarides@hotmail.com
Requires-Python: >=3.8,<4.0
Classifier: Development Status :: 4 - Beta
Classifier: Intended Audience :: Developers
Classifier: License :: OSI Approved :: MIT License
Classifier: Operating System :: OS Independent
Classifier: Programming Language :: Python :: 3
Classifier: Programming Language :: Python :: 3.8
Classifier: Programming Language :: Python :: 3.9
Classifier: Programming Language :: Python :: 3.10
Classifier: Programming Language :: Python :: 3.11
Classifier: Topic :: Software Development :: Libraries :: Python Modules
Requires-Dist: requests (>=2.26.0,<3.0.0)
Project-URL: Repository, https://github.com/atsangarides/pyngeso
